MANIFEST.in
README.txt
setup.py
XStatic_objectpath.egg-info/PKG-INFO
XStatic_objectpath.egg-info/SOURCES.txt
XStatic_objectpath.egg-info/dependency_links.txt
XStatic_objectpath.egg-info/namespace_packages.txt
XStatic_objectpath.egg-info/not-zip-safe
XStatic_objectpath.egg-info/top_level.txt
xstatic/__init__.py
xstatic/pkg/__init__.py
xstatic/pkg/objectpath/__init__.py
xstatic/pkg/objectpath/data/ObjectPath.js