Metadata-Version: 1.0
Name: XStatic-objectpath
Version: 1.2.1.0
Summary: objectpath 1.2.1 (XStatic packaging standard)
Home-page: https://github.com/mike-marcacci/objectpath
Author: Rob Cresswell
Author-email: robert.cresswell@outlook.com
License: MIT
Keywords: objectpath xstatic
Platform: any
